napari_tiler/__init__.py
napari_tiler/_tests/__init__.py
napari_tiler/_tests/test_dock_widget.py
napari_tiler/merger_widget.py
napari_tiler/napari.yaml
napari_tiler/tiler_widget.py
napari_tiler-0.1.0.dist-info/METADATA
napari_tiler-0.1.0.dist-info/WHEEL
napari_tiler-0.1.0.dist-info/entry_points.txt
napari_tiler-0.1.0.dist-info/licenses/LICENSE
napari_tiler-0.1.0.dist-info/RECORD
