Metadata-Version: 2.4
Name: napari-tiler
Version: 0.1.0
Summary: N-dimensional tiling and merging support for napari
License: LICENCE
License-File: LICENSE
Author: Tim Morello
Author-email: tdmorello@gmail.com
Requires-Python: >=3.10,<3.13
Classifier: Development Status :: 2 - Pre-Alpha
Classifier: Framework :: napari
Classifier: Intended Audience :: Developers
Classifier: License :: OSI Approved :: BSD License
Classifier: License :: Other/Proprietary License
Classifier: Operating System :: OS Independent
Classifier: Programming Language :: Python
Classifier: Programming Language :: Python :: 3
Classifier: Programming Language :: Python :: 3.10
Classifier: Programming Language :: Python :: 3.11
Classifier: Programming Language :: Python :: 3.12
Classifier: Programming Language :: Python :: 3 :: Only
Classifier: Topic :: Software Development :: Testing
Requires-Dist: importlib-metadata (<4.3) ; python_version < "3.8"
Requires-Dist: numpy (>=1.21.4,<2.0.0)
Requires-Dist: tiler (>=0.6.0,<0.7.0)
Project-URL: Bug Tracker, https://github.com/tdmorello/napari-tiler/issues
Project-URL: Documentation, https://github.com/tdmorello/napari-tiler#README.md
Project-URL: Source Code, https://github.com/tdmorello/napari-tiler
Project-URL: User Support, https://github.com/tdmorello/napari-tiler/issues
